[
  {
    "nome": "César Moulin",
    "email": "lourenomassari@gmail.com",
    "password": "test@123_",
    "administrador": "true",
    "_id": "0ABEC9puA7mz8Eku"
  },
  {
    "nome": "Fulano da Silva",
    "email": "stsznbtl@emailteste.com",
    "password": "teste",
    "administrador": "true",
    "_id": "0EoMGH1mszEytmdT"
  },
  {
    "nome": "Fulano da Silva",
    "email": "zzprawe@emailteste.com",
    "password": "teste",
    "administrador": "true",
    "_id": "0nC1bSFzvCn3dTb6"
  },
  {
    "nome": "Fulano da Silva",
    "email": "fulano@qa.com",
    "password": "teste",
    "administrador": "true",
    "_id": "0uxuPY0cbmQhpEz1"
  },
  {
    "nome": "Bruna Furtado",
    "email": "saraalmeida@gmail.com",
    "password": "test@123_",
    "administrador": "true",
    "_id": "3LKlGUXFc5IginXv"
  },
  {
    "nome": "fulano do teste",
    "email": "mypf@email.com",
    "password": "1234",
    "administrador": "true",
    "_id": "3SLB4U19CT5YBL2O"
  },
  {
    "nome": "Fulano da Silva",
    "email": "qpyljtq@emailteste.com",
    "password": "teste",
    "administrador": "true",
    "_id": "4ApSzj32Y3uLPxRx"
  },
  {
    "nome": "Lucas Sartori",
    "email": "rodrigopesca@gmail.com",
    "password": "test@123_",
    "administrador": "true",
    "_id": "73sAESoIU9OofTmd"
  },
  {
    "nome": "Fulano da Silva",
    "email": "clorjs@emailteste.com",
    "password": "teste",
    "administrador": "true",
    "_id": "82a7JlYCvNhPEt1a"
  },
  {
    "nome": "Fulano da Silva",
    "email": "eykyrx@emailteste.com",
    "password": "teste",
    "administrador": "true",
    "_id": "9Sm3nx4KtDX9afgQ"
  },
  {
    "nome": "Emanuela Braggion",
    "email": "jonasmachado@gmail.com",
    "password": "test@123_",
    "administrador": "true",
    "_id": "BjlWaPQGBPKCD9t6"
  },
  {
    "nome": "Fulano da Silva",
    "email": "fzeyrt@emailteste.com",
    "password": "teste",
    "administrador": "true",
    "_id": "GppeC4IRdPi3bbL0"
  },
  {
    "nome": "Fulano da Silva",
    "email": "pwpw@emailteste.com",
    "password": "1234",
    "administrador": "true",
    "_id": "HK9hP9sUaRp8Pt7V"
  },
  {
    "nome": "Rodrigo Marquioro",
    "email": "elisalozano@gmail.com",
    "password": "test@123_",
    "administrador": "true",
    "_id": "Ij1iJod5ju5mCt2A"
  },
  {
    "nome": "Fulano da Silva",
    "email": "gcjcv@emailteste.com",
    "password": "teste",
    "administrador": "true",
    "_id": "JkYlzwoD7N3Paon5"
  },
  {
    "nome": "Lara Bellon",
    "email": "viniciosdolago@gmail.com",
    "password": "test@123_",
    "administrador": "true",
    "_id": "KTIbunD74EZ9M2hj"
  },
  {
    "nome": "Fulano da Silva",
    "email": "qjxztpj@emailteste.com",
    "password": "teste",
    "administrador": "true",
    "_id": "LCzz4OHWFRMwfQ4w"
  },
  {
    "nome": "Thiago Carrasco",
    "email": "karenfitipaldi@gmail.com",
    "password": "test@123_",
    "administrador": "true",
    "_id": "MQNZtQ6008vsI1U1"
  },
  {
    "nome": "fulano do teste",
    "email": "hlsy@email.com",
    "password": "1234",
    "administrador": "true",
    "_id": "NhbstkZcOMtMt7qo"
  },
  {
    "nome": "Theo Meato",
    "email": "calebedolago@gmail.com",
    "password": "test@123_",
    "administrador": "true",
    "_id": "OXZGxLLiAdnNk1Ci"
  },
  {
    "nome": "Fulano da Silva",
    "email": "dbdt@emailteste.com",
    "password": "1234",
    "administrador": "true",
    "_id": "PCj6LegQRiborDta"
  },
  {
    "nome": "Fulano da Silva",
    "email": "hiyvig@emailteste.com",
    "password": "teste",
    "administrador": "true",
    "_id": "PQUWEdRaTNZSyQH3"
  },
  {
    "nome": "Fulano da Silva",
    "email": "zrzd@emailteste.com",
    "password": "1234",
    "administrador": "true",
    "_id": "Qsm07A8s2s7eUIkb"
  },
  {
    "nome": "Qa",
    "email": "qa@gg.br",
    "password": "123456789",
    "administrador": "true",
    "_id": "R3QhwpA0ot960Yfe"
  },
  {
    "nome": "Fulano da Silva",
    "email": "jsidn@emailteste.com",
    "password": "teste",
    "administrador": "true",
    "_id": "RVO8dnCD4iN5W21d"
  },
  {
    "nome": "Enzo Tavares",
    "email": "micaelaluca@gmail.com",
    "password": "test@123_",
    "administrador": "true",
    "_id": "RiZriuUhvY1zgGZ9"
  },
  {
    "nome": "Iara Nicole",
    "email": "leticiacamata@gmail.com",
    "password": "test@123_",
    "administrador": "true",
    "_id": "T8GvbW5FMuaSoIUQ"
  },
  {
    "nome": "Emanuel Marin",
    "email": "valentimdibarrel@gmail.com",
    "password": "test@123_",
    "administrador": "true",
    "_id": "TVqu9lvI1m4ottPo"
  },
  {
    "nome": "Fulano da Silva",
    "email": "jxsovm@emailteste.com",
    "password": "teste",
    "administrador": "true",
    "_id": "VMhqSsLur35bfHKL"
  },
  {
    "nome": "Fulano da Silva",
    "email": "qddteyua@emailteste.com",
    "password": "teste",
    "administrador": "true",
    "_id": "W1CrcFVwQOs5jEuW"
  },
  {
    "nome": "Lorena Gobbato",
    "email": "bryanthomaz@gmail.com",
    "password": "test@123_",
    "administrador": "true",
    "_id": "WUAsj3x424KCYVJv"
  },
  {
    "nome": "Fulano da Silva",
    "email": "tmvz@emailteste.com",
    "password": "1234",
    "administrador": "true",
    "_id": "Wfi5T97wrtBxhcP3"
  },
  {
    "nome": "Fulano da Silva",
    "email": "yiok@emailteste.com",
    "password": "1234",
    "administrador": "true",
    "_id": "X7Ywed8SrAMPk7LO"
  },
  {
    "nome": "Aarã Battistella",
    "email": "micaeladardengo@gmail.com",
    "password": "test@123_",
    "administrador": "true",
    "_id": "YMxKlzKzo72jriqz"
  },
  {
    "nome": "Fulano da Silva",
    "email": "wiab@emailteste.com",
    "password": "1234",
    "administrador": "true",
    "_id": "aT9caHI6ufAv1KNF"
  },
  {
    "nome": "Joaquim Sagers",
    "email": "rebecapaulina@gmail.com",
    "password": "test@123_",
    "administrador": "true",
    "_id": "bIos8wvrWJVoP7P3"
  },
  {
    "nome": "Fulano da Silva",
    "email": "niabfzj@emailteste.com",
    "password": "teste",
    "administrador": "true",
    "_id": "bYMuUez3qbnvO0hD"
  },
  {
    "nome": "Fulano da Silva",
    "email": "beltrano@qa.com.br",
    "password": "teste",
    "administrador": "true",
    "_id": "dXIFz71DDV58PIBF"
  },
  {
    "nome": "Fulano da Silva",
    "email": "xocndi@emailteste.com",
    "password": "teste",
    "administrador": "true",
    "_id": "eMEPZ7SVOUibGaSj"
  },
  {
    "nome": "Fulano da Silva",
    "email": "xwra@emailteste.com",
    "password": "1234",
    "administrador": "true",
    "_id": "eYqbawpz2lcTGVc5"
  },
  {
    "nome": "Fulano da Silva",
    "email": "jmwozm@emailteste.com",
    "password": "teste",
    "administrador": "true",
    "_id": "gKc5wqK8x6pSiVt2"
  },
  {
    "nome": "Lucas Sancao",
    "email": "brunavaliati@gmail.com",
    "password": "test@123_",
    "administrador": "true",
    "_id": "i3BAJysKlGTUzIpR"
  },
  {
    "nome": "Fulano da Silva",
    "email": "lzbh@emailteste.com",
    "password": "1234",
    "administrador": "true",
    "_id": "iDqivBPAHsYb8UD3"
  },
  {
    "nome": "Davi Verret",
    "email": "benjamincarazas@gmail.com",
    "password": "test@123_",
    "administrador": "true",
    "_id": "jV8g0EDNgsY9fN9T"
  },
  {
    "nome": "Kevin Marchioro",
    "email": "biancamascarelo@gmail.com",
    "password": "test@123_",
    "administrador": "true",
    "_id": "jetxkUSHphsnsvKG"
  },
  {
    "nome": "Fulano da Silva",
    "email": "zkts@emailteste.com",
    "password": "1234",
    "administrador": "true",
    "_id": "lPfmSzYXgD6UxQxR"
  },
  {
    "nome": "Fulano da Silva",
    "email": "lkcp@emailteste.com",
    "password": "1234",
    "administrador": "true",
    "_id": "mMlRi3l83yFqCq7F"
  },
  {
    "nome": "Lara Romanini",
    "email": "lorenzobullock@gmail.com",
    "password": "test@123_",
    "administrador": "true",
    "_id": "mWY4II9Qsp5ESJ7t"
  },
  {
    "nome": "Fulano da Silva",
    "email": "kjhl@emailteste.com",
    "password": "1234",
    "administrador": "true",
    "_id": "mXhJZFOumpiU06Tv"
  },
  {
    "nome": "Fulano da Silva",
    "email": "stcb@emailteste.com",
    "password": "1234",
    "administrador": "true",
    "_id": "n0fehjkrFumwAwUI"
  },
  {
    "nome": "fulano do teste",
    "email": "htfw@email.com",
    "password": "1234",
    "administrador": "true",
    "_id": "wX3v12c4wo8YfoUp"
  },
  {
    "nome": "Fulano da Silva",
    "email": "zyxy@emailteste.com",
    "password": "1234",
    "administrador": "true",
    "_id": "xT0hm9ApLWQ6FW3v"
  },
  {
    "nome": "Fulano da Silva",
    "email": "zcyyt@emailteste.com",
    "password": "teste",
    "administrador": "true",
    "_id": "yUZf7JKiCJLPtKgz"
  }
]